duplicati_client/__init__.py
duplicati_client/arg_parser.py
duplicati_client/auth.py
duplicati_client/common.py
duplicati_client/compatibility.py
duplicati_client/config.py
duplicati_client/duplicati_client.py
duplicati_client/helper.py
duplicati_client/requests_wrapper.py
duplicati_client/test_duplicati_client.py
duplicati_client-0.5.7b10.dist-info/LICENSE.txt
duplicati_client-0.5.7b10.dist-info/METADATA
duplicati_client-0.5.7b10.dist-info/WHEEL
duplicati_client-0.5.7b10.dist-info/entry_points.txt
duplicati_client-0.5.7b10.dist-info/top_level.txt
duplicati_client-0.5.7b10.dist-info/RECORD
