Metadata-Version: 2.1
Name: duplicati-client
Version: 0.5.7b10
Summary: A command-line tool for controlling remote or local Duplicti servers
Home-page: https://github.com/pectojin/duplicati-client
Author: Rune Henriksen
Author-email: contact@henriksen.dk
License: LGPL-2.1
Platform: UNKNOWN
Requires-Dist: PyYaml
Requires-Dist: python-dateutil
Requires-Dist: requests
